quokka/__init__.py
quokka/__main__.py
quokka/cli.py
quokka/admin/__init__.py
quokka/admin/actions.py
quokka/admin/ajax.py
quokka/admin/fields.py
quokka/admin/formatters.py
quokka/admin/forms.py
quokka/admin/views.py
quokka/admin/widgets.py
quokka/admin/wtforms_html5.py
quokka/core/__init__.py
quokka/core/app.py
quokka/core/auth.py
quokka/core/blueprints.py
quokka/core/commands_collector.py
quokka/core/context_processors.py
quokka/core/db.py
quokka/core/error_handlers.py
quokka/core/errors.py
quokka/core/flask_dynaconf.py
quokka/core/logger.py
quokka/core/monitoring.py
quokka/core/regex_url_support.py
quokka/core/template_filters.py
quokka/core/themes.py
quokka/core/content/__init__.py
quokka/core/content/admin.py
quokka/core/content/formats.py
quokka/core/content/models.py
quokka/core/content/paginator.py
quokka/core/content/parsers.py
quokka/core/content/utils.py
quokka/core/content/views.py
quokka/core/views/__init__.py
quokka/core/views/sitemap.py
quokka/module_template/README.md
quokka/module_template/setup.py
quokka/module_template/quokka_module_template/__init__.py
quokka/module_template/quokka_module_template/admin.py
quokka/project_template/.gitignore
quokka/project_template/.secrets.yml
quokka/project_template/quokka.yml
quokka/project_template/wsgi.py
quokka/project_template/databases/README.md
quokka/project_template/modules/README.md
quokka/project_template/output/README.md
quokka/project_template/static/favicon.ico
quokka/project_template/themes/README.md
quokka/project_template/themes/Flex/.gitignore
quokka/project_template/themes/Flex/.travis.yml
quokka/project_template/themes/Flex/LICENSE
quokka/project_template/themes/Flex/README.md
quokka/project_template/themes/Flex/static/font-awesome/css/font-awesome.min.css
quokka/project_template/themes/Flex/static/font-awesome/fonts/FontAwesome.otf
quokka/project_template/themes/Flex/static/font-awesome/fonts/fontawesome-webfont.eot
quokka-0.4.0.dist-info/DESCRIPTION.rst
quokka-0.4.0.dist-info/METADATA
quokka-0.4.0.dist-info/RECORD
quokka-0.4.0.dist-info/WHEEL
quokka-0.4.0.dist-info/entry_points.txt
quokka-0.4.0.dist-info/metadata.json
quokka-0.4.0.dist-info/pbr.json
quokka-0.4.0.dist-info/top_level.txt
