Metadata-Version: 2.0
Name: quokka
Version: 0.4.0
Summary: Content Management Framework for Python
Home-page: https://github.com/rochacbruno/quokka
Author: Bruno Rocha
Author-email: rochacbruno@gmail.com
License: BSD License
Keywords: cms content management flask static site blog
Platform: UNKNOWN
Classifier: Development Status :: 4 - Beta
Classifier: Environment :: Web Environment
Classifier: Intended Audience :: Developers
Classifier: Intended Audience :: Information Technology
Classifier: License :: OSI Approved :: BSD License
Classifier: Operating System :: OS Independent
Classifier: Programming Language :: Python
Classifier: Programming Language :: Python :: 3
Classifier: Programming Language :: Python :: 3.6
Classifier: Topic :: Internet :: WWW/HTTP :: Dynamic Content
Classifier: Topic :: Software Development :: Libraries :: Python Modules
Requires-Dist: flask
Requires-Dist: import-string
Requires-Dist: flask-admin
Requires-Dist: wtforms-components
Requires-Dist: pymongo (==2.4.1)
Requires-Dist: tinymongo
Requires-Dist: tinydb-serialization
Requires-Dist: manage
Requires-Dist: dynaconf
Requires-Dist: quokka-flask-htmlbuilder
Requires-Dist: awesome-slugify
Requires-Dist: flask-babelex
Requires-Dist: mistune
Requires-Dist: flask-simplelogin
Requires-Dist: frozen-flask
Requires-Dist: pillow
Requires-Dist: pyrss2gen
Requires-Dist: requests
Requires-Dist: pygments
Requires-Dist: six
